cyberfusion/RabbitMQConsumerLogServer/__init__.py
cyberfusion/RabbitMQConsumerLogServer/api.py
cyberfusion/RabbitMQConsumerLogServer/database.py
cyberfusion/RabbitMQConsumerLogServer/dependencies.py
cyberfusion/RabbitMQConsumerLogServer/fastapi.py
cyberfusion/RabbitMQConsumerLogServer/gui.py
cyberfusion/RabbitMQConsumerLogServer/pydantic_models.py
cyberfusion/RabbitMQConsumerLogServer/seeders.py
cyberfusion/RabbitMQConsumerLogServer/settings.py
cyberfusion/RabbitMQConsumerLogServer/utilities.py
python3_cyberfusion_rabbitmq_consumer_log_server-1.2.dist-info/METADATA
python3_cyberfusion_rabbitmq_consumer_log_server-1.2.dist-info/WHEEL
python3_cyberfusion_rabbitmq_consumer_log_server-1.2.dist-info/entry_points.txt
python3_cyberfusion_rabbitmq_consumer_log_server-1.2.dist-info/top_level.txt
python3_cyberfusion_rabbitmq_consumer_log_server-1.2.dist-info/RECORD
