Metadata-Version: 2.4
Name: python3-cyberfusion-rabbitmq-consumer-log-server
Version: 1.2
Summary: Log server for RabbitMQ consumer.
Author-email: Cyberfusion <support@cyberfusion.io>
Project-URL: Source, https://github.com/CyberfusionIO/python3-cyberfusion-rabbitmq-consumer-log-server
Requires-Dist: fastapi==0.115.11
Requires-Dist: pydantic==2.10.6
Requires-Dist: alembic==1.13.2
Requires-Dist: SQLAlchemy==2.0.40
Requires-Dist: jinja2==3.1.6
Requires-Dist: pydantic-settings==2.8.1
